dbOperation/__init__.py
dbOperation/main.py
dbOperation-0.0.1.dist-info/License.txt
dbOperation-0.0.1.dist-info/METADATA
dbOperation-0.0.1.dist-info/WHEEL
dbOperation-0.0.1.dist-info/top_level.txt
dbOperation-0.0.1.dist-info/RECORD
